reviewpanel/__init__.py
reviewpanel/admin.py
reviewpanel/apps.py
reviewpanel/forms.py
reviewpanel/migrations/0001_initial.py
reviewpanel/migrations/0002_alter_input_options_cohort_allow_skip.py
reviewpanel/migrations/0003_alter_cohort_inputs_alter_panel_panelists_and_more.py
reviewpanel/migrations/0004_cohort_size.py
reviewpanel/migrations/0005_presentation_options.py
reviewpanel/migrations/0006_alter_cohortmember_object_id_alter_score_object_id_and_more.py
reviewpanel/migrations/0007_metric_display_values.py
reviewpanel/migrations/0008_input_show_in_index_alter_metric_input.py
reviewpanel/migrations/0009_alter_template_program_and_initial_data.py
reviewpanel/migrations/__init__.py
reviewpanel/models.py
reviewpanel/signals.py
reviewpanel/static/css/markdown.css
reviewpanel/static/css/reset.css
reviewpanel/static/css/reviewpanel.css
reviewpanel/static/css/submission.css
reviewpanel/static/img/rp_icons/audio.png
reviewpanel/static/img/rp_icons/generic.png
reviewpanel/static/js/submission.js
reviewpanel/templates/admin/reviewpanel/add_to_cohort.html
reviewpanel/templates/admin/reviewpanel/add_to_panel.html
reviewpanel/templates/admin/reviewpanel/cohort/change_form.html
reviewpanel/templates/admin/reviewpanel/cohort_status.html
reviewpanel/templates/admin/reviewpanel/export_forms.html
reviewpanel/templates/admin/reviewpanel/panel/submit_line.html
reviewpanel/templates/admin/reviewpanel/panelists_confirmation.html
reviewpanel/templates/admin/reviewpanel/report_submissions.html
reviewpanel/templates/reviewpanel/base.html
reviewpanel/templates/reviewpanel/form_complete.html
reviewpanel/templates/reviewpanel/form_index.html
reviewpanel/templates/reviewpanel/item_file.html
reviewpanel/templates/reviewpanel/item_selector.html
reviewpanel/templates/reviewpanel/program_index.html
reviewpanel/templates/reviewpanel/submission.html
reviewpanel/templates/reviewpanel/submission_inputs.html
reviewpanel/templates/reviewpanel/submission_metrics.html
reviewpanel-0.8.5.dist-info/entry_points.txt
reviewpanel-0.8.5.dist-info/LICENSE
reviewpanel-0.8.5.dist-info/WHEEL
reviewpanel-0.8.5.dist-info/METADATA
reviewpanel-0.8.5.dist-info/RECORD
