Metadata-Version: 2.1
Name: reviewpanel
Version: 0.8.5
Summary: Formative plugin for reviewing and scoring applicant submissions
Home-page: https://github.com/johncronan/reviewpanel
License: LGPL-2.1
Keywords: review,panel,score,formative
Author: John Kyle Cronan
Requires-Python: >=3.8,<4.0
Classifier: Development Status :: 2 - Pre-Alpha
Classifier: Environment :: Web Environment
Classifier: Framework :: Django
Classifier: Framework :: Django :: 3.1
Classifier: Framework :: Django :: 3.2
Classifier: Framework :: Django :: 4
Classifier: Framework :: Django :: 4.0
Classifier: Intended Audience :: System Administrators
Classifier: License :: OSI Approved
Classifier: License :: OSI Approved :: GNU Lesser General Public License v2 (LGPLv2)
Classifier: Programming Language :: Python
Classifier: Programming Language :: Python :: 3
Classifier: Programming Language :: Python :: 3.10
Classifier: Programming Language :: Python :: 3.11
Classifier: Programming Language :: Python :: 3.8
Classifier: Programming Language :: Python :: 3.9
Classifier: Topic :: Internet :: WWW/HTTP :: Dynamic Content
Classifier: Topic :: Internet :: WWW/HTTP :: WSGI :: Application
Classifier: Topic :: Multimedia
Classifier: Topic :: Office/Business :: Groupware
Requires-Dist: backports.zoneinfo; python_version >= "3.8" and python_version < "3.9"
Requires-Dist: formative (>=0.9.9)
Project-URL: Repository, https://github.com/johncronan/reviewpanel
